sphinxcontrib/drawio/__init__.py
sphinxcontrib/drawio/drawio.css
sphinxcontrib_drawio-0.0.17.dist-info/LICENSE
sphinxcontrib_drawio-0.0.17.dist-info/METADATA
sphinxcontrib_drawio-0.0.17.dist-info/WHEEL
sphinxcontrib_drawio-0.0.17.dist-info/top_level.txt
sphinxcontrib_drawio-0.0.17.dist-info/RECORD
