Metadata-Version: 2.1
Name: sphinxcontrib-drawio
Version: 0.0.17
Summary: Sphinx Extension to include draw.io files
Home-page: https://github.com/Modelmat/sphinxcontrib-drawio
Author: Modelmat
Author-email: modelmat@outlook.com.au
License: MIT
Classifier: Programming Language :: Python :: 3
Classifier: License :: OSI Approved :: MIT License
Classifier: Operating System :: OS Independent
Classifier: Framework :: Sphinx :: Extension
Requires-Python: >=3.6
License-File: LICENSE
Requires-Dist: sphinx (>=2)
